zuydbot_api/APIConnection.py
zuydbot_api/__init__.py
zuydbot_api-0.1.dist-info/METADATA
zuydbot_api-0.1.dist-info/WHEEL
zuydbot_api-0.1.dist-info/top_level.txt
zuydbot_api-0.1.dist-info/RECORD
