Metadata-Version: 2.1
Name: zuydbot-api
Version: 0.1
Summary: API Wrapper for Zuydbot
Home-page: https://gitlab.com/zuydbot/zuydbot-api-wrapper
Author: Alain Lardinois
Author-email: alain@ip-ict.nl
License: UNKNOWN
Platform: UNKNOWN
